valx/__init__.py
valx/models/classifier_upgraded.pkl
valx/models/count_vectorizer.sav
valx/models/decision_tree_model.sav
valx-0.2.5.dist-info/licenses/LICENSE
valx-0.2.5.dist-info/METADATA
valx-0.2.5.dist-info/WHEEL
valx-0.2.5.dist-info/top_level.txt
valx-0.2.5.dist-info/RECORD
